src/__init__.py
src/sr.py
pysr_mcranmer-0.0.1.dist-info/LICENSE
pysr_mcranmer-0.0.1.dist-info/METADATA
pysr_mcranmer-0.0.1.dist-info/WHEEL
pysr_mcranmer-0.0.1.dist-info/top_level.txt
pysr_mcranmer-0.0.1.dist-info/RECORD
