Metadata-Version: 2.1
Name: pysr-mcranmer
Version: 0.0.1
Summary: Simple and efficient symbolic regression
Home-page: https://github.com/MilesCranmer/pysr
Author: Miles Cranmer
Author-email: miles.cranmer@gmail.com
License: UNKNOWN
Platform: UNKNOWN
Classifier: Programming Language :: Python :: 3
Classifier: Operating System :: OS Independent
Requires-Python: >=3.3
